[
  {
    "id": 2,
    "name": "data",
    "content": "data",
    "category": "input",
    "selected": false,
    "params": {
      "datasetType": "",
      "datasetId": ""
    },
    "template": "frontend/components/layers/data/node-test-2.svg"
  },
  {
    "id": 2,
    "name": "convol",
    "content": "convolution",
    "category": "layer",
    "selected": false,
    "params": {
      "filtersCount": "",
      "filterWidth": "",
      "filterHeight": "",
      "activationFunction": "",
      "subsamplingType": "",
      "subsamplingSize": ""
    },
    "template": "frontend/components/layers/convol/node-test-2.svg"
  },
  {
    "id": 3,
    "name": "dense",
    "content": "dense",
    "category": "layer",
    "selected": false,
    "params": {
      "activationFunction": "",
      "neuronsCount": ""
    },
    "template": "frontend/components/layers/dense/node-test-4.svg"
  },
  {
    "id": 4,
    "name": "solver",
    "content": "solver",
    "category": "output",
    "selected": false,
    "params": {
      "lossFunction": "",
      "epochsCount": "",
      "snapshotInterval": "",
      "validationInterval": "",
      "batchSize": "",
      "learningRate": "",
      "optimizer": ""
    },
    "template": "frontend/components/layers/solver/node-test-4.svg"
  }
]